pymod/__init__.py
pymod/__main__.py
pymod/cli.py
pymod/manager.py
pymod/shell.py
pymod-0.2.dist-info/METADATA
pymod-0.2.dist-info/RECORD
pymod-0.2.dist-info/WHEEL
pymod-0.2.dist-info/entry_points.txt
pymod-0.2.dist-info/top_level.txt
