Metadata-Version: 2.1
Name: pymod
Version: 0.2
Summary: Simple Environment Variable Manager
Home-page: https://github.com/chengscott/pymod
Author: chengscott
Maintainer: chengscott
License: BSD
Platform: UNKNOWN
Classifier: Development Status :: 3 - Alpha
Classifier: Environment :: Console
Classifier: Intended Audience :: Developers
Classifier: Intended Audience :: System Administrators
Classifier: License :: OSI Approved :: BSD License
Classifier: Topic :: System :: Shells
